2005/CS.v
`timescale 1ns/10ps
module CS(Y, X, reset, clk);

input  clk, reset; 
input  [7:0] X;
output reg [9:0] Y;

reg [7:0] XS [0:8];
reg [9:0] X_appr;
reg [11:0] Sum;
wire [9:0] X_avg;

integer i, k, z, e;

// Count Sum of 9 numbers from XS
always @(posedge clk or posedge reset) begin
    if(reset) begin
        Sum <= 0;
        for (z = 0; z < 9 ; z = z + 1 )  
            XS[z] <= 0;
    end
    else begin
        /* update XS and X_avg using the concept of "Sliding Window" */
        // update Sum
        Sum <= Sum + X - XS[0];
        // Left Shifting each index creating space for new input
        for(i = 1; i <= 8; i = i + 1) XS[i-1] <= XS[i]; 
        // Add new input into XS
        XS[8] <= X;
    end
end

 // update X_avg
assign  X_avg =  Sum / 9;

// Count Appr
always @(*) begin
    X_appr = 0; 
    // if X_avg equals to one of the XS, then X_appr <= X_avg
    for(k = 0; k < 9; k = k + 1) begin 
        if( (XS[k] <= X_avg) && (XS[k] > X_appr) ) 
            X_appr = XS[k];
    end
end

// Determine Output Y
assign Y = ( Sum + ( (X_appr << 3) + X_appr ) ) >> 3;

endmodule

2005/testfixture.v
`timescale 1ns/10ps
`define CYCLE  10        	// Modify your clock period here
//`define SDFFILE "cs_syn.sdf"	// Modify your sdf file name
`define INFILE "in.dat"
`define OUTFILE "out_golden.dat"  

module test;
parameter INPUT_DATA = `INFILE;
parameter GOLDEN = `OUTFILE;
parameter N_PAT = 2000;
parameter t_reset = `CYCLE*2;

reg reset;
reg clk;
reg ready;
reg stop;
reg flag1, flag2;
wire pclk = clk ;

integer i, out_f, err, pattern_num;
integer a, b;
reg     [7:0] X;
reg 	[7:0] data_base1 [0:20000];
reg	[9:0] data_base2 [0:20000];
reg 	[9:0] data_tmp;
wire    [9:0] Y; 

CS top (.Y(Y), .X(X), .reset(reset), .clk(clk)); 

//initial $sdf_annotate(`SDFFILE, top);

initial	$readmemh (INPUT_DATA, data_base1);

initial $readmemh (GOLDEN, data_base2);

initial begin
   reset = 1'b0;
   clk = 1'b1;
   stop = 1'b0;
   err = 0;
   a = 0;
   b = 0;
   pattern_num = 0 ;     
end

initial begin
$dumpfile("cs.vcd");
$dumpvars;
//$fsdbDumpfile("cs.fsdb");
//$fsdbDumpvars; 

   out_f = $fopen("out.dat");
   if (out_f == 0) begin
        $display("Output file open error !");
        $finish;
   end
end

always begin #(`CYCLE/2) clk = ~clk;
end


specify
$setup(Y, posedge pclk, 0.5, flag1);
$hold(posedge pclk, Y, 0.5, flag2); 
endspecify 

always @(flag1)
   if(flag1 == 1'b1 || flag1 == 1'b0)
     a = a +1;

always @(flag2)
   if(flag2 == 1'b1  || flag2 == 1'b0)
     b = b +1;


initial 
  begin
    X = data_base1[0] ;
    @(negedge clk) reset = 1'b1;
    #t_reset reset = 1'b0;  ready = 1'b0;
    #`CYCLE
    for (i = 1; i < N_PAT; i = i + 1) 
    begin
      @(negedge clk) X = data_base1[i]; 
      if (i==8)
        @(posedge clk) ready = 1'b1;                      
    end 
  end  
 		
always @(posedge clk) 
  begin
   if (pattern_num + 9 > N_PAT)      stop = 1 ;
   else if (ready) 
     begin
       data_tmp = data_base2[pattern_num]; 
       $fdisplay(out_f,"%h", Y); 
         if (Y !== data_tmp) 
           begin
             $display("ERROR at %d:output %h !=expect %h ",pattern_num, Y, data_tmp);
             err = err + 1 ;
           end
       pattern_num = pattern_num + 1 ; 
     end

  end  

initial begin
      @(posedge stop)
      $display("---------------------------------------------\n");
      if (a !=0)
         $display("There are %d setup time violations by Y\n", a);
      if (b !=0)
         $display("There are %d hold time violations by Y\n", b);
      $display("---------------------------------------------\n");
      if (err == 0)
        begin
          $display("All data have been generated successfully!\n");
          $display("-------------------PASS-------------------\n");
        end
      else 
         $display("There are %d errors!\n", err);
      $display("---------------------------------------------\n");
      $finish;
   end
endmodule

2005/cs.vcd
$date
	Fri Feb 23 10:29:50 2024
$end
$version
	ModelSim Version 2020.1
$end
$timescale
	10ps
$end

$scope module test $end
$var parameter 48 ! INPUT_DATA $end
$var parameter 112 " GOLDEN $end
$var parameter 32 # N_PAT $end
$var parameter 32 $ t_reset $end
$var reg 1 % reset $end
$var reg 1 & clk $end
$var reg 1 ' ready $end
$var reg 1 ( stop $end
$var reg 1 ) flag1 $end
$var reg 1 * flag2 $end
$var wire 1 + pclk $end
$var integer 32 , i $end
$var integer 32 - out_f $end
$var integer 32 . err $end
$var integer 32 / pattern_num $end
$var integer 32 0 a $end
$var integer 32 1 b $end
$var reg 8 2 X [7:0] $end
$var reg 10 3 data_tmp [9:0] $end
$var wire 1 4 Y [9] $end
$var wire 1 5 Y [8] $end
$var wire 1 6 Y [7] $end
$var wire 1 7 Y [6] $end
$var wire 1 8 Y [5] $end
$var wire 1 9 Y [4] $end
$var wire 1 : Y [3] $end
$var wire 1 ; Y [2] $end
$var wire 1 < Y [1] $end
$var wire 1 = Y [0] $end

$scope module top $end
$var wire 1 > clk $end
$var wire 1 ? reset $end
$var wire 1 @ X [7] $end
$var wire 1 A X [6] $end
$var wire 1 B X [5] $end
$var wire 1 C X [4] $end
$var wire 1 D X [3] $end
$var wire 1 E X [2] $end
$var wire 1 F X [1] $end
$var wire 1 G X [0] $end
$var reg 10 H Y [9:0] $end
$var reg 10 I X_appr [9:0] $end
$var reg 12 J Sum [11:0] $end
$var wire 1 K X_avg [9] $end
$var wire 1 L X_avg [8] $end
$var wire 1 M X_avg [7] $end
$var wire 1 N X_avg [6] $end
$var wire 1 O X_avg [5] $end
$var wire 1 P X_avg [4] $end
$var wire 1 Q X_avg [3] $end
$var wire 1 R X_avg [2] $end
$var wire 1 S X_avg [1] $end
$var wire 1 T X_avg [0] $end
$var integer 32 U i $end
$var integer 32 V k $end
$var integer 32 W z $end
$var integer 32 X e $end
$upscope $end
$upscope $end
$enddefinitions $end
#0
$dumpvars
0%
1&
x'
0(
x)
x*
b10001111 2
bx 3
b0xxxxxxxxx H
b0 I
bx J
b11111010000 #
b10100 $
b11010010110111000101110011001000110000101110100 !
b110111101110101011101000101111101100111011011110110110001100100011001010110111000101110011001000110000101110100 "
bx ,
b10 -
b0 .
b0 /
b0 0
b0 1
b1001 U
b1001 V
bx W
bx X
1+
x=
x<
x;
x:
x9
x8
x7
x6
x5
04
xT
xS
xR
xQ
xP
xO
xN
xM
xL
xK
1>
0?
1G
1F
1E
1D
0C
0B
0A
1@
$end
#500
0&
0+
0>
1%
1?
b0 W
b1 W
b10 W
b11 W
b100 W
b101 W
b110 W
b111 W
b1000 W
b1001 W
b0 J
b0 H
0=
0<
0;
0:
09
08
07
06
05
0T
0S
0R
0Q
0P
0O
0N
0M
0L
0K
b0 V
b1 V
b10 V
b11 V
b100 V
b101 V
b110 V
b111 V
b1000 V
b1001 V
#1000
1&
1+
1>
b0 W
b1 W
b10 W
b11 W
b100 W
b101 W
b110 W
b111 W
b1000 W
b1001 W
#1500
0&
0+
0>
#2000
1&
1+
1>
b0 W
b1 W
b10 W
b11 W
b100 W
b101 W
b110 W
b111 W
b1000 W
b1001 W
#2500
0%
0'
0&
0+
0?
0>
#3000
1&
1+
1>
b1 U
b10 U
b11 U
b100 U
b101 U
b110 U
b111 U
b1000 U
b1001 U
b10001111 J
b10001 H
1=
19
1T
1S
1R
1Q
b0 V
b1 V
b10 V
b11 V
b100 V
b101 V
b110 V
b111 V
b1000 V
b1001 V
#3500
b1 ,
0&
0+
0>
b1011 2
b10 ,
0E
0@
#4000
1&
1+
1>
b1 U
b10 U
b11 U
b100 U
b101 U
b110 U
b111 U
b1000 U
b1001 U
b10011010 J
b10011 H
1<
0S
0R
0Q
1P
b0 V
b1 V
b10 V
b11 V
b100 V
b101 V
b110 V
b111 V
b1000 V
b1011 I
b1001 V
b11111 H
1;
1:
#4500
0&
0+
0>
b1011101 2
b11 ,
0F
1E
1C
1A
#5000
1&
1+
1>
b1 U
b10 U
b11 U
b100 U
b101 U
b110 U
b111 U
b1000 U
b1001 U
b11110111 J
b101011 H
0;
09
18
1S
1Q
b0 I
b0 V
b1 V
b10 V
b11 V
b100 V
b101 V
b110 V
b111 V
b1011 I
b1000 V
b1001 V
#5500
0&
0+
0>
b100000 2
b100 ,
0G
0E
0D
0C
1B
0A
#6000
1&
1+
1>
b1 U
b10 U
b11 U
b100 U
b101 U
b110 U
b111 U
b1000 U
b1001 U
b100010111 J
b101111 H
1;
1R
b0 I
b0 V
b1 V
b10 V
b11 V
b100 V
b101 V
b110 V
b1011 I
b111 V
b1000 V
b1001 V
#6500
0&
0+
0>
b11110011 2
b101 ,
1G
1F
1C
1A
1@
#7000
1&
1+
1>
b1 U
b10 U
b11 U
b100 U
b101 U
b110 U
b111 U
b1000 U
b1001 U
b1000001010 J
b1001101 H
0<
08
17
0T
0R
1O
b0 I
b0 V
b1 V
b10 V
b11 V
b100 V
b101 V
b1011 I
b110 V
b111 V
b100000 I
b1000 V
b1001 V
b1100101 H
0:
18
#7500
0&
0+
0>
b111110 2
b110 ,
0G
1E
1D
0A
0@
#8000
1&
1+
1>
b1 U
b10 U
b11 U
b100 U
b101 U
b110 U
b111 U
b1000 U
b1001 U
b1001001000 J
b1101101 H
1:
0S
0Q
0P
0O
1N
b0 I
b0 V
b1 V
b10 V
b11 V
b100 V
b1011 I
b101 V
b110 V
b100000 I
b111 V
b1000 V
b111110 I
b1001 V
b10001110 H
0=
1<
08
07
16
#8500
0&
0+
0>
b11100101 2
b111 ,
1G
0F
0D
0C
1A
1@
#9000
1&
1+
1>
b1 U
b10 U
b11 U
b100 U
b101 U
b110 U
b111 U
b1000 U
b1001 U
b1100101101 J
b10101011 H
1=
0;
18
1S
1Q
1P
b0 I
b0 V
b1 V
b10 V
b11 V
b1011 I
b100 V
b101 V
b100000 I
b110 V
b111 V
b111110 I
b1000 V
b1001 V
#9500
0&
0+
0>
b11 2
b1000 ,
1F
0E
0B
0A
0@
#10000
1&
1+
1>
b1 U
b10 U
b11 U
b100 U
b101 U
b110 U
b111 U
b1000 U
b1001 U
b1100110000 J
b0 I
b0 V
b1 V
b10 V
b1011 I
b11 V
b100 V
b100000 I
b101 V
b110 V
b111110 I
b111 V
b1000 V
b1001 V
#10500
0&
0+
0>
b1100 2
0G
0F
1E
1D
#11000
1&
1+
1>
b1 U
b10 U
b11 U
b100 U
b101 U
b110 U
b111 U
b1000 U
b1001 U
1'
b1001 ,
b1100111100 J
b10101101 H
0<
1;
0S
1R
b0 I
b0 V
b1 V
b1011 I
b10 V
b11 V
b100000 I
b100 V
b101 V
b111110 I
b110 V
b111 V
b1000 V
b1001 V
#11500
0&
0+
0>
b1110100 2
b1010 ,
0D
1C
1B
1A
#12000
1&
1+
1>
b1 U
b10 U
b11 U
b100 U
b101 U
b110 U
b111 U
b1000 U
b1001 U
b10101101 3
b1 /
b1100100001 J
b10101001 H
0;
1T
0R
b0 I
b0 V
b1011 I
b1 V
b10 V
b100000 I
b11 V
b100 V
b111110 I
b101 V
b110 V
b111 V
b1000 V
b1001 V
#12500
0&
0+
0>
b1111001 2
b1011 ,
1G
0E
1D
#13000
1&
1+
1>
b1 U
b10 U
b11 U
b100 U
b101 U
b110 U
b111 U
b1000 U
b1001 U
b10101001 3
b10 /
b1110001111 J
b10110111 H
1<
1;
0:
19
1R
0Q
0P
1O
b0 I
b0 V
b1011101 I
b1 V
b10 V
b11 V
b100 V
b101 V
b110 V
b111 V
b1000 V
b1001 V
b11011010 H
0=
0;
1:
08
17
#13500
0&
0+
0>
b1 2
b1100 ,
0D
0C
0B
0A
#14000
1&
1+
1>
b1 U
b10 U
b11 U
b100 U
b101 U
b110 U
b111 U
b1000 U
b1001 U
b11011010 3
b11 /
b1100110011 J
b11001111 H
1=
1;
09
1S
0R
1Q
1P
0O
b0 I
b0 V
b100000 I
b1 V
b10 V
b111110 I
b11 V
b100 V
b101 V
b110 V
b111 V
b1000 V
b1001 V
b10101100 H
0=
0<
18
07
#14500
0&
0+
0>
b110000 2
b1101 ,
0G
1C
1B
#15000
1&
1+
1>
b1 U
b10 U
b11 U
b100 U
b101 U
b110 U
b111 U
b1000 U
b1001 U
b10101100 3
b100 /
b1101000011 J
b10101110 H
1<
0T
0S
1R
b0 I
b0 V
b1 V
b111110 I
b10 V
b11 V
b100 V
b101 V
b110 V
b111 V
b1000 V
b1001 V
#15500
0&
0+
0>
b101110 2
b1110 ,
1F
1E
1D
0C
#16000
1&
1+
1>
b1 U
b10 U
b11 U
b100 U
b101 U
b110 U
b111 U
b1000 U
b1001 U
b10101110 3
b101 /
b1001111110 J
b10010101 H
1=
0<
0:
19
08
1S
0Q
0P
b0 I
b0 V
b111110 I
b1 V
b10 V
b11 V
b100 V
b101 V
b110 V
b111 V
b1000 V
b1001 V
#16500
0&
0+
0>
b10100100 2
b1111 ,
0F
0D
1@
#17000
1&
1+
1>
b1 U
b10 U
b11 U
b100 U
b101 U
b110 U
b111 U
b1000 U
b1001 U
b10010101 3
b110 /
b1011100100 J
b10100010 H
0=
1<
0;
09
18
0R
1P
b0 I
b0 V
b1 V
b11 I
b10 V
b1100 I
b11 V
b100 V
b101 V
b110 V
b110000 I
b111 V
b1000 V
b1001 V
b10010010 H
19
08
#17500
0&
0+
0>
b1110110 2
b10000 ,
1F
1C
1A
0@
#18000
1&
1+
1>
b1 U
b10 U
b11 U
b100 U
b101 U
b110 U
b111 U
b1000 U
b1001 U
b10010010 3
b111 /
b1001110101 J
b10000100 H
0<
1;
09
1T
0S
1R
0P
b0 I
b0 V
b11 I
b1 V
b1100 I
b10 V
b11 V
b100 V
b101 V
b110000 I
b110 V
b111 V
b1000 V
b1001 V
#18500
0&
0+
0>
b10000100 2
b10001 ,
0F
0C
0B
0A
1@
#19000
1&
1+
1>
b1 U
b10 U
b11 U
b100 U
b101 U
b110 U
b111 U
b1000 U
b1001 U
b10000100 3
b1000 /
b1011110110 J
b10010100 H
19
0T
1P
b0 I
b0 V
b1100 I
b1 V
b10 V
b11 V
b100 V
b110000 I
b101 V
b110 V
b111 V
b1000 V
b1001 V
#19500
0&
0+
0>
b1010001 2
b10010 ,
1G
0E
1C
1A
0@
#20000
1&
1+
1>
b1 U
b10 U
b11 U
b100 U
b101 U
b110 U
b111 U
b1000 U
b1001 U
b10010100 3
b1001 /
b1100111011 J
b10011101 H
1=
1:
1T
1S
0R
1Q
b0 I
b0 V
b1 V
b10 V
b1 I
b11 V
b110000 I
b100 V
b101 V
b110 V
b111 V
b1000 V
b1010001 I
b1001 V
b11000010 H
0=
1<
0;
0:
09
17
#20500
0&
0+
0>
b11010110 2
b10011 ,
0G
1F
1E
1@
#21000
1&
1+
1>
b1 U
b10 U
b11 U
b100 U
b101 U
b110 U
b111 U
b1000 U
b1001 U
b11000010 3
b1010 /
b1110011101 J
b11001110 H
1;
1:
0T
1R
0Q
0P
1O
b0 I
b0 V
b1 V
b1 I
b10 V
b110000 I
b11 V
b100 V
b101 V
b110 V
b111 V
b1010001 I
b1000 V
b1001 V
#21500
0&
0+
0>
b1110000 2
b10100 ,
0F
0E
1B
0@
#22000
1&
1+
1>
b1 U
b10 U
b11 U
b100 U
b101 U
b110 U
b111 U
b1000 U
b1001 U
b11001110 3
b1011 /
b1110010100 J
b11001101 H
1=
0<
1T
0S
b0 I
b0 V
b1 I
b1 V
b110000 I
b10 V
b11 V
b100 V
b101 V
b110 V
b1010001 I
b111 V
b1000 V
b1001 V
#22500
0&
0+
0>
b110101 2
b10101 ,
1G
1E
0A
#23000
1&
1+
1>
b1 U
b10 U
b11 U
b100 U
b101 U
b110 U
b111 U
b1000 U
b1001 U
b11001101 3
b1100 /
b1111001000 J
b11010100 H
0=
0:
19
1S
0R
1Q
b0 I
b0 V
b110000 I
b1 V
b10 V
b11 V
b100 V
b101 V
b1010001 I
b110 V
b111 V
b1000 V
b1001 V
#23500
0&
0+
0>
b10000 2
b10110 ,
0G
0E
0B
#24000
1&
1+
1>
b1 U
b10 U
b11 U
b100 U
b101 U
b110 U
b111 U
b1000 U
b1001 U
b11010100 3
b1101 /
b1110101000 J
b11010000 H
0;
0T
0S
b0 I
b0 V
b101110 I
b1 V
b10 V
b11 V
b100 V
b1010001 I
b101 V
b110 V
b111 V
b1000 V
b1001 V
#24500
0&
0+
0>
b100011 2
b10111 ,
1G
1F
0C
1B
#25000
1&
1+
1>
b1 U
b10 U
b11 U
b100 U
b101 U
b110 U
b111 U
b1000 U
b1001 U
b11010000 3
b1110 /
b1110011101 J
b11001110 H
1<
1;
1:
09
1S
1R
0Q
b0 I
b0 V
b1 V
b10 V
b11 V
b1010001 I
b100 V
b101 V
b110 V
b111 V
b1000 V
b1001 V
#25500
0&
0+
0>
b11100111 2
b11000 ,
1E
1A
1@
#26000
1&
1+
1>
b1 U
b10 U
b11 U
b100 U
b101 U
b110 U
b111 U
b1000 U
b1001 U
b11001110 3
b1111 /
b1111100000 J
b11010111 H
1=
0:
19
1Q
b0 I
b0 V
b1 V
b10 V
b1010001 I
b11 V
b100 V
b101 V
b110 V
b111 V
b1000 V
b1001 V
#26500
0&
0+
0>
b111011 2
b11001 ,
0E
1D
1C
0A
0@
#27000
1&
1+
1>
b1 U
b10 U
b11 U
b100 U
b101 U
b110 U
b111 U
b1000 U
b1001 U
b11010111 3
b10000 /
b1110100101 J
b11001111 H
1:
09
1T
0Q
b0 I
b0 V
b1 V
b1010001 I
b10 V
b11 V
b100 V
b101 V
b110 V
b111 V
b1000 V
b1001 V
#27500
0&
0+
0>
b1101101 2
b11010 ,
0F
1E
0C
1A
#28000
1&
1+
1>
b1 U
b10 U
b11 U
b100 U
b101 U
b110 U
b111 U
b1000 U
b1001 U
b11001111 3
b10001 /
b1110001110 J
b11001100 H
0=
0<
0S
b0 I
b0 V
b1010001 I
b1 V
b10 V
b11 V
b100 V
b101 V
b110 V
b111 V
b1000 V
b1001 V
#28500
0&
0+
0>
b110100 2
b11011 ,
0G
0D
1C
0A
#29000
1&
1+
1>
b1 U
b10 U
b11 U
b100 U
b101 U
b110 U
b111 U
b1000 U
b1001 U
b11001100 3
b10010 /
b1101110001 J
b11001001 H
1=
0;
0R
b0 I
b0 V
b1 V
b10 V
b110101 I
b11 V
b100 V
b101 V
b110 V
b111011 I
b111 V
b1000 V
b1001 V
b10110000 H
0=
0:
19
18
07
#29500
0&
0+
0>
b1100001 2
b11100 ,
1G
0E
0C
1A
#30000
1&
1+
1>
b1 U
b10 U
b11 U
b100 U
b101 U
b110 U
b111 U
b1000 U
b1001 U
b10110000 3
b10011 /
b1011111100 J
b10100001 H
1=
09
0T
1R
1P
0O
b0 I
b0 V
b1 V
b110101 I
b10 V
b11 V
b100 V
b101 V
b111011 I
b110 V
b111 V
b1000 V
b1001 V
#30500
0&
0+
0>
b10001001 2
b11101 ,
1D
0B
0A
1@
#31000
1&
1+
1>
b1 U
b10 U
b11 U
b100 U
b101 U
b110 U
b111 U
b1000 U
b1001 U
b10100001 3
b10100 /
b1100010101 J
b10100101 H
1;
1T
1S
b0 I
b0 V
b110101 I
b1 V
b10 V
b11 V
b100 V
b111011 I
b101 V
b110 V
b111 V
b1000 V
b1001 V
#31500
0&
0+
0>
b10111111 2
b11110 ,
1F
1E
1C
1B
#32000
1&
1+
1>
b1 U
b10 U
b11 U
b100 U
b101 U
b110 U
b111 U
b1000 U
b1001 U
b10100101 3
b10101 /
b1110011111 J
b10110110 H
0=
1<
19
0P
1O
b0 I
b0 V
b10000 I
b1 V
b100011 I
b10 V
b11 V
b111011 I
b100 V
b101 V
b110 V
b1100001 I
b111 V
b1000 V
b1001 V
b11100001 H
1=
0<
0;
09
17
#32500
0&
0+
0>
b11011100 2
b11111 ,
0G
0F
0B
1A
#33000
1&
1+
1>
b1 U
b10 U
b11 U
b100 U
b101 U
b110 U
b111 U
b1000 U
b1001 U
b11100001 3
b10110 /
b10001101011 J
b11111010 H
0=
1<
1:
19
0S
1Q
1P
b0 I
b0 V
b100011 I
b1 V
b10 V
b111011 I
b11 V
b1101101 I
b100 V
b101 V
b110 V
b111 V
b1000 V
b1001 V
b100001000 H
0<
09
08
07
06
15
#33500
0&
0+
0>
b11010011 2
b100000 ,
1G
1F
0E
0D
#34000
1&
1+
1>
b1 U
b10 U
b11 U
b100 U
b101 U
b110 U
b111 U
b1000 U
b1001 U
b100001000 3
b10111 /
b10100011011 J
b100011110 H
1<
1;
19
0R
0Q
0O
0N
1M
b0 I
b0 V
b1 V
b111011 I
b10 V
b1101101 I
b11 V
b100 V
b101 V
b10001001 I
b110 V
b111 V
b1000 V
b1001 V
b100111101 H
1=
0<
18
#34500
0&
0+
0>
b10011100 2
b100001 ,
0G
0F
1E
1D
0A
#35000
1&
1+
1>
b1 U
b10 U
b11 U
b100 U
b101 U
b110 U
b111 U
b1000 U
b1001 U
b100111101 3
b11000 /
b10011010000 J
b100110100 H
0=
0:
0T
1Q
0P
b0 I
b0 V
b111011 I
b1 V
b1101101 I
b10 V
b11 V
b100 V
b101 V
b110 V
b111 V
b1000 V
b1001 V
b100010100 H
08
#35500
0&
0+
0>
b10001111 2
b100010 ,
1G
1F
0C
#36000
1&
1+
1>
b1 U
b10 U
b11 U
b100 U
b101 U
b110 U
b111 U
b1000 U
b1001 U
b100010100 3
b11001 /
b10100100100 J
b100011111 H
1=
1<
1:
1S
0Q
1P
b0 I
b0 V
b1101101 I
b1 V
b10 V
b11 V
b10001001 I
b100 V
b101 V
b110 V
b111 V
b1000 V
b10001111 I
b1001 V
b101000101 H
0<
0:
09
17
#36500
0&
0+
0>
b11111000 2
b100011 ,
0G
0F
0E
1C
1B
1A
#37000
1&
1+
1>
b1 U
b10 U
b11 U
b100 U
b101 U
b110 U
b111 U
b1000 U
b1001 U
b101000101 3
b11010 /
b10110101111 J
b101010110 H
0=
1<
19
1T
0S
0P
1O
b0 I
b0 V
b110100 I
b1 V
b1100001 I
b10 V
b10001001 I
b11 V
b100 V
b101 V
b110 V
b10011100 I
b111 V
b1000 V
b1001 V
b101100101 H
1=
0<
09
18
#37500
0&
0+
0>
b11101001 2
b100100 ,
1G
0C
#38000
1&
1+
1>
b1 U
b10 U
b11 U
b100 U
b101 U
b110 U
b111 U
b1000 U
b1001 U
b101100101 3
b11011 /
b11001100100 J
b101111100 H
0=
1:
19
1R
1P
b0 I
b0 V
b1100001 I
b1 V
b10001001 I
b10 V
b11 V
b100 V
b101 V
b10011100 I
b110 V
b111 V
b1000 V
b1001 V
#38500
0&
0+
0>
b1010000 2
b100101 ,
0G
0D
1C
0B
0@
#39000
1&
1+
1>
b1 U
b10 U
b11 U
b100 U
b101 U
b110 U
b111 U
b1000 U
b1001 U
b101111100 3
b11100 /
b11001010011 J
b101111001 H
1=
0;
1S
0R
b0 I
b0 V
b10001001 I
b1 V
b10 V
b11 V
b100 V
b10011100 I
b101 V
b110 V
b111 V
b1000 V
b1001 V
#39500
0&
0+
0>
b10100011 2
b100110 ,
1G
1F
0C
1B
0A
1@
#40000
1&
1+
1>
b1 U
b10 U
b11 U
b100 U
b101 U
b110 U
b111 U
b1000 U
b1001 U
b101111001 3
b11101 /
b11001101101 J
b101111101 H
1;
0T
1R
b0 I
b0 V
b1 V
b10 V
b11 V
b10011100 I
b100 V
b101 V
b110 V
b111 V
b1000 V
b10100011 I
b1001 V
b110000101 H
0:
09
08
07
16
#40500
0&
0+
0>
b11111011 2
b100111 ,
1D
1C
1A
#41000
1&
1+
1>
b1 U
b10 U
b11 U
b100 U
b101 U
b110 U
b111 U
b1000 U
b1001 U
b110000101 3
b11110 /
b11010101001 J
b110001100 H
0=
1:
1T
0S
1Q
b0 I
b0 V
b1 V
b10 V
b10011100 I
b11 V
b100 V
b101 V
b110 V
b111 V
b10100011 I
b1000 V
b1001 V
#41500
0&
0+
0>
b10000011 2
b101000 ,
0D
0C
0B
0A
#42000
1&
1+
1>
b1 U
b10 U
b11 U
b100 U
b101 U
b110 U
b111 U
b1000 U
b1001 U
b110001100 3
b11111 /
b11001010000 J
b110000001 H
1=
0;
0:
1S
0R
0Q
b0 I
b0 V
b1 V
b10011100 I
b10 V
b11 V
b100 V
b101 V
b110 V
b10100011 I
b111 V
b1000 V
b1001 V
#42500
0&
0+
0>
b1101100 2
b101001 ,
0G
0F
1E
1D
1B
1A
0@
#43000
1&
1+
1>
b1 U
b10 U
b11 U
b100 U
b101 U
b110 U
b111 U
b1000 U
b1001 U
b110000001 3
b100000 /
b10111101001 J
b101110100 H
0=
1;
19
18
17
06
0T
0S
1Q
0P
b0 I
b0 V
b10011100 I
b1 V
b10 V
b11 V
b100 V
b101 V
b10100011 I
b110 V
b111 V
b1000 V
b1001 V
#43500
0&
0+
0>
b10110000 2
b101010 ,
0E
0D
1C
0A
1@
#44000
1&
1+
1>
b1 U
b10 U
b11 U
b100 U
b101 U
b110 U
b111 U
b1000 U
b1001 U
b101110100 3
b100001 /
b10111111101 J
b101110111 H
1=
1<
1S
b0 I
b0 V
b10001111 I
b1 V
b10 V
b11 V
b100 V
b10100011 I
b101 V
b110 V
b111 V
b1000 V
b1001 V
#44500
0&
0+
0>
b1100100 2
b101011 ,
1E
0C
1A
0@
#45000
1&
1+
1>
b1 U
b10 U
b11 U
b100 U
b101 U
b110 U
b111 U
b1000 U
b1001 U
b101110111 3
b100010 /
b10111010010 J
b101110001 H
0<
0;
1T
0S
1R
0Q
b0 I
b0 V
b1 V
b10 V
b1010000 I
b11 V
b10100011 I
b100 V
b101 V
b110 V
b111 V
b1000 V
b1001 V
#45500
0&
0+
0>
b1010 2
b101100 ,
1F
0E
1D
0B
0A
#46000
1&
1+
1>
b1 U
b10 U
b11 U
b100 U
b101 U
b110 U
b111 U
b1000 U
b1001 U
b101110001 3
b100011 /
b10011100100 J
b101010011 H
1<
08
1S
0R
1Q
0O
b0 I
b0 V
b1 V
b1010000 I
b10 V
b11 V
b100 V
b10000011 I
b101 V
b110 V
b111 V
b1000 V
b1001 V
b100101111 H
1;
1:
09
18
07
#46500
0&
0+
0>
b11000101 2
b101101 ,
1G
0F
1E
0D
1A
1@
#47000
1&
1+
1>
b1 U
b10 U
b11 U
b100 U
b101 U
b110 U
b111 U
b1000 U
b1001 U
b100101111 3
b100100 /
b10011000000 J
b100101011 H
0;
1R
0Q
b0 I
b0 V
b1010000 I
b1 V
b10 V
b11 V
b10000011 I
b100 V
b101 V
b110 V
b111 V
b1000 V
b1001 V
#47500
0&
0+
0>
b1011010 2
b101110 ,
0G
1F
0E
1D
1C
0@
#48000
1&
1+
1>
b1 U
b10 U
b11 U
b100 U
b101 U
b110 U
b111 U
b1000 U
b1001 U
b100101011 3
b100101 /
b10011001010 J
b100101100 H
0=
0<
1;
0T
0S
0R
1Q
b0 I
b0 V
b1 V
b10 V
b10000011 I
b11 V
b100 V
b101 V
b110 V
b111 V
b1000 V
b1001 V
#48500
0&
0+
0>
b100 2
b101111 ,
0F
1E
0D
0C
0A
#49000
1&
1+
1>
b1 U
b10 U
b11 U
b100 U
b101 U
b110 U
b111 U
b1000 U
b1001 U
b100101100 3
b100110 /
b10000101011 J
b100011000 H
0;
19
08
1S
1R
0Q
1P
1O
1N
0M
b0 I
b0 V
b1 V
b10 V
b1101100 I
b11 V
b100 V
b101 V
b110 V
b111 V
b1000 V
b1001 V
b11111110 H
1<
1;
18
17
16
05
#49500
0&
0+
0>
b1111001 2
b110000 ,
1G
0E
1D
1C
1B
1A
#50000
1&
1+
1>
b1 U
b10 U
b11 U
b100 U
b101 U
b110 U
b111 U
b1000 U
b1001 U
b11111110 3
b100111 /
b1110101001 J
b11101110 H
09
0S
0R
1Q
0P
b0 I
b0 V
b1 V
b10 V
b11 V
b1100100 I
b100 V
b101 V
b110 V
b111 V
b1000 V
b1001 V
b11100101 H
1=
0<
0:
#50500
0&
0+
0>
b101 2
b110001 ,
1E
0D
0C
0B
0A
#51000
1&
1+
1>
b1 U
b10 U
b11 U
b100 U
b101 U
b110 U
b111 U
b1000 U
b1001 U
b11100101 3
b101000 /
b1100101011 J
b11010101 H
19
08
1S
1P
0O
b0 I
b0 V
b1 V
b10 V
b11 V
b1010 I
b100 V
b101 V
b1011010 I
b110 V
b111 V
b1000 V
b1001 V
b11001010 H
0=
1<
0;
1:
09
#51500
0&
0+
0>
b10011000 2
b110010 ,
0G
0E
1D
1C
1@
#52000
1&
1+
1>
b1 U
b10 U
b11 U
b100 U
b101 U
b110 U
b111 U
b1000 U
b1001 U
b11001010 3
b101001 /
b1101010111 J
b11010000 H
0<
0:
19
1T
1R
b0 I
b0 V
b1 V
b10 V
b1010 I
b11 V
b100 V
b1011010 I
b101 V
b110 V
b111 V
b1000 V
b1001 V
#52500
0&
0+
0>
b111010 2
b110011 ,
1F
1B
0@
#53000
1&
1+
1>
b1 U
b10 U
b11 U
b100 U
b101 U
b110 U
b111 U
b1000 U
b1001 U
b11010000 3
b101010 /
b1011100001 J
b11000001 H
1=
09
0S
0R
0Q
b0 I
b0 V
b1 V
b1010 I
b10 V
b11 V
b100 V
b101 V
b110 V
b111 V
b1000 V
b111010 I
b1001 V
b10011101 H
1;
1:
19
07
#53500
0&
0+
0>
b111011 2
b110100 ,
1G
#54000
1&
1+
1>
b1 U
b10 U
b11 U
b100 U
b101 U
b110 U
b111 U
b1000 U
b1001 U
b10011101 3
b101011 /
b1010111000 J
b10011000 H
0=
0;
1R
1Q
0P
b0 I
b0 V
b1010 I
b1 V
b10 V
b11 V
b100 V
b101 V
b110 V
b111 V
b111010 I
b1000 V
b111011 I
b1001 V
b10011001 H
1=
#54500
0&
0+
0>
b11000011 2
b110101 ,
0D
0C
0B
1A
1@
