2007/lcd_ctrl.v
module lcd_ctrl(clk, reset, datain, cmd, cmd_valid, dataout, output_valid, busy);
input                clk;
input                reset;
input        [7:0]   datain;
input        [2:0]   cmd;
input                cmd_valid;
output  reg  [7:0]   dataout;
output  reg          output_valid;
output  reg          busy;

        reg  [7:0]   graph     [0:35];
        reg  [1:0]   originX;
        reg  [1:0]   originY;
        reg  [2:0]   currentX;
        reg  [2:0]   currentY;
        reg  [5:0]   input_counter;
        reg  [2:0]   stage;

integer i;

always @(negedge clk or posedge reset) begin
    if(reset) begin
        stage <= 0;
        busy <= 0;
    end
    else begin
        if(cmd_valid) begin
            busy <= 2'd1;
            stage <= cmd;
        end
    end
end

always @(posedge clk or posedge reset) begin 
    if(reset) begin
        input_counter <= 6'd0;

        currentX <= 3'd2;
        currentY <= 3'd2;
        originX <= 2'd2;
        originY <= 2'd2;
        output_valid <= 0;
        for(i = 0; i < 36; i = i + 1)
            graph[i] <= 8'd0;
    end
    else begin
        /* Load Data */
        if(!cmd_valid && busy && stage == 3'b001) begin
            if(input_counter < 36) begin
                graph[input_counter] <= datain;
                input_counter <= input_counter + 1;
            end
            else begin
                // output logic
                if(originX == currentX && originY == currentY) begin
                    output_valid <= 1;
                    originX <= 2;
                    originY <= 2;
                    currentX <= originX;
                    currentY <= originY;
                end
                // output logic
                dataout <= graph[6 * currentY + currentX];
                // update currentX and currentY
                if(currentX == originX + 3'd2) begin
                    // Finished Printing
                    if(currentY == originY + 3'd2) begin
                        busy <= 0;
                        output_valid <= 0;
                        input_counter <= 0;
                    end
                    else begin
                        currentX <= originX;
                        currentY <= currentY + 1;
                    end
                end
                else begin
                    currentX <= currentX + 1;
                end
            end
        end
        /* Cmd except for Load Data*/
        else if(!cmd_valid && busy) begin
            if(originX == currentX && originY == currentY) begin
                // update currentX and currentY 
                if(stage == 3'b010)      originX <= originX >= 2'd3 ? 2'd3 : originX + 1;      /*  Shift Right    */
                else if(stage == 3'b011) originX <= originX <= 2'd0 ? 2'd0 : originX - 1;     /*   Shift Left    */
                else if(stage == 3'b100) originY <= originY <= 2'd0 ? 2'd0 : originY - 1;    /*    Shift Up     */
                else if(stage == 3'b101) originY <= originY <= 2'd3 ? 2'd3 : originY + 1;   /*     Shift Down  */
                // Update originX and originY
                output_valid <= 1;
                currentX <= originX;
                currentY <= originY;
            end
            // output logic
            dataout <= graph[6 * currentY + currentX];
            // update currentX and currentY
            if(currentX == originX + 3'd2) begin
                // Finished Printing
                if(currentY == originY + 3'd2) begin
                    busy <= 0;
                    output_valid <= 0;
                    input_counter <= 0;
                end
                else begin
                    currentX <= originX;
                    currentY <= currentY + 1;
                end
            end
            else begin
                currentX <= currentX + 1;
            end
        end
    end
end
                                                                                     
endmodule

2007/testfixture.v
`timescale 1ns/10ps
`define CYCLE    10                        // Modify your clock period here
`define SDFFILE  "./LCD_CTRL.sdf"	    // Modify your sdf file name
`define IMAGE    "./image2.dat"             // Modify your test image file: image1.dat or image2.dat
`define CMD      "./cmd2.dat"               // Modify your test cmd file: cmd1.dat or cmd2.dat
`define EXPECT   "./out_golden2.dat"        // Modify your output golden file: out_golden1.dat or out_golden2.dat

module test;
parameter IMAGE_N_PAT = 36;         // 6x6 = 36 pixels
parameter CMD_N_PAT = 30;           // number of commands
parameter OUT_LENGTH = 270;         // output length = (3x3) * CMD_N_PAT
parameter t_reset = `CYCLE*2;

reg           clk;
reg           reset;
reg   [7:0]   datain;
reg   [2:0]   cmd;
reg           cmd_valid;
wire  [7:0]   dataout;
wire          output_valid;
wire          busy;

reg   [7:0]   image_mem [0:IMAGE_N_PAT-1];
reg   [2:0]   cmd_mem   [0:CMD_N_PAT-1];
reg   [7:0]   out_mem   [0:OUT_LENGTH-1];
reg   [7:0]   out_temp;

reg           stop;
integer       i, j, out_f, err, pattern_num;
reg           over;

   lcd_ctrl top(.clk(clk), .reset(reset), .datain(datain), 
                .cmd(cmd), .cmd_valid(cmd_valid), .dataout(dataout), 
                .output_valid(output_valid), .busy(busy));          
   


//initial $sdf_annotate(`SDFFILE, top);

initial	$readmemh (`IMAGE,  image_mem);
initial	$readmemh (`CMD,    cmd_mem);
initial	$readmemh (`EXPECT, out_mem);

initial begin
   clk         = 1'b0;
   reset       = 1'b0;
   cmd_valid   = 1'b0;
   stop        = 1'b0;  
   over        = 1'b0;
   pattern_num = 0;
   err         = 0;    
end

always begin #(`CYCLE/2) clk = ~clk; end

initial begin
$dumpfile("LCD_CTRL.vcd");
$dumpvars;
//$fsdbDumpfile("LCD_CTRL.fsdb");
//$fsdbDumpvars;

   out_f = $fopen("out.dat");
   if (out_f == 0) begin
        $display("Output file open error !");
        $finish;
   end
end


initial begin
   @(negedge clk)  reset = 1'b1;
   #t_reset        reset = 1'b0;
   
   @(negedge clk)    i=0;
   while (i <= CMD_N_PAT) begin               
      if(!busy) begin
        cmd = cmd_mem[i];
        cmd_valid = 1'b1;  
        
        if(cmd_mem[i] === 3'h1) begin    //cmd: Load data        
           for(j=0; j<=IMAGE_N_PAT; j=j+1)begin
              @(negedge clk) datain = image_mem[j];
                             cmd = 'hz; cmd_valid = 1'b0;
           end
           i = i+1;
        end
        else begin                      //cmd: other command
           @(negedge clk) datain='hz; cmd_valid = 1'b0; i = i+1;
        end       
      end 
      else begin
         datain='hz; cmd = 'hz;  cmd_valid = 0;
         @(negedge clk);
      end               
    end                                       
    stop = 1 ;      
end

always @(posedge clk)begin
   out_temp = out_mem[pattern_num];
   if(output_valid)begin
      $fdisplay(out_f,"%h", dataout);
      if(dataout !== out_temp) begin
         $display("ERROR at %d:output %h !=expect %h ",pattern_num, dataout, out_temp);
         err = err + 1 ;
      end
      pattern_num = pattern_num + 1;      
   end
   if(pattern_num === OUT_LENGTH)  over = 1'b1;
end


initial begin
      @(posedge stop)      
      if((over) || (pattern_num!='h0)) begin
         $display("---------------------------------------------\n");
         if (err == 0)  begin
            $display("All data have been generated successfully!\n");
            $display("-------------------PASS-------------------\n");
         end
         else 
            $display("There are %d errors!\n", err);
            $display("---------------------------------------------\n");
      end
      else begin
        $display("---------------------------------------------\n");
        $display("Error!!! There is no any data output ...!\n");
        $display("-------------------FAIL-------------------\n");
        $display("---------------------------------------------\n");
      end
      $finish;
end
   
endmodule

2007/LCD_CTRL.vcd
$date
	Sat Feb 24 21:59:22 2024
$end
$version
	ModelSim Version 2020.1
$end
$timescale
	10ps
$end

$scope module test $end
$var parameter 32 ! IMAGE_N_PAT $end
$var parameter 32 " CMD_N_PAT $end
$var parameter 32 # OUT_LENGTH $end
$var parameter 32 $ t_reset $end
$var reg 1 % clk $end
$var reg 1 & reset $end
$var reg 8 ' datain [7:0] $end
$var reg 3 ( cmd [2:0] $end
$var reg 1 ) cmd_valid $end
$var wire 1 * dataout [7] $end
$var wire 1 + dataout [6] $end
$var wire 1 , dataout [5] $end
$var wire 1 - dataout [4] $end
$var wire 1 . dataout [3] $end
$var wire 1 / dataout [2] $end
$var wire 1 0 dataout [1] $end
$var wire 1 1 dataout [0] $end
$var wire 1 2 output_valid $end
$var wire 1 3 busy $end
$var reg 8 4 out_temp [7:0] $end
$var reg 1 5 stop $end
$var integer 32 6 i $end
$var integer 32 7 j $end
$var integer 32 8 out_f $end
$var integer 32 9 err $end
$var integer 32 : pattern_num $end
$var reg 1 ; over $end

$scope module top $end
$var wire 1 < clk $end
$var wire 1 = reset $end
$var wire 1 > datain [7] $end
$var wire 1 ? datain [6] $end
$var wire 1 @ datain [5] $end
$var wire 1 A datain [4] $end
$var wire 1 B datain [3] $end
$var wire 1 C datain [2] $end
$var wire 1 D datain [1] $end
$var wire 1 E datain [0] $end
$var wire 1 F cmd [2] $end
$var wire 1 G cmd [1] $end
$var wire 1 H cmd [0] $end
$var wire 1 I cmd_valid $end
$var reg 8 J dataout [7:0] $end
$var reg 1 K output_valid $end
$var reg 1 L busy $end
$var reg 2 M originX [1:0] $end
$var reg 2 N originY [1:0] $end
$var reg 3 O currentX [2:0] $end
$var reg 3 P currentY [2:0] $end
$var reg 6 Q input_counter [5:0] $end
$var reg 3 R stage [2:0] $end
$var integer 32 S i $end
$upscope $end
$upscope $end
$enddefinitions $end
#0
$dumpvars
0%
0&
bx '
bx (
0)
bx 4
05
0;
bx J
xK
xL
bx M
bx N
bx O
bx P
bx Q
bx R
b100100 !
b11110 "
b100001110 #
b10100 $
bx 6
bx 7
b10 8
b0 9
b0 :
bx S
x1
x0
x/
x.
x-
x,
x+
x*
x2
x3
0I
xH
xG
xF
xE
xD
xC
xB
xA
x@
x?
x>
0=
0<
$end
#500
1%
1<
b1100110 4
#1000
0%
0<
1&
1=
b0 S
b1 S
b10 S
b11 S
b100 S
b101 S
b110 S
b111 S
b1000 S
b1001 S
b1010 S
b1011 S
b1100 S
b1101 S
b1110 S
b1111 S
b10000 S
b10001 S
b10010 S
b10011 S
b10100 S
b10101 S
b10110 S
b10111 S
b11000 S
b11001 S
b11010 S
b11011 S
b11100 S
b11101 S
b11110 S
b11111 S
b100000 S
b100001 S
b100010 S
b100011 S
b100100 S
b0 R
0L
b0 Q
b10 O
b10 P
b10 M
b10 N
0K
03
02
#1500
1%
1<
b0 S
b1 S
b10 S
b11 S
b100 S
b101 S
b110 S
b111 S
b1000 S
b1001 S
b1010 S
b1011 S
b1100 S
b1101 S
b1110 S
b1111 S
b10000 S
b10001 S
b10010 S
b10011 S
b10100 S
b10101 S
b10110 S
b10111 S
b11000 S
b11001 S
b11010 S
b11011 S
b11100 S
b11101 S
b11110 S
b11111 S
b100000 S
b100001 S
b100010 S
b100011 S
b100100 S
#2000
0%
0<
#2500
1%
1<
b0 S
b1 S
b10 S
b11 S
b100 S
b101 S
b110 S
b111 S
b1000 S
b1001 S
b1010 S
b1011 S
b1100 S
b1101 S
b1110 S
b1111 S
b10000 S
b10001 S
b10010 S
b10011 S
b10100 S
b10101 S
b10110 S
b10111 S
b11000 S
b11001 S
b11010 S
b11011 S
b11100 S
b11101 S
b11110 S
b11111 S
b100000 S
b100001 S
b100010 S
b100011 S
b100100 S
#3000
0&
0%
0=
0<
b0 6
b1 (
1)
b0 7
1H
0G
0F
1I
#3500
1%
1<
#4000
0%
0<
b100000 '
bz (
0)
b1 7
zH
zG
zF
0E
0D
0C
0B
0A
1@
0?
0>
0I
1L
b1 R
13
#4500
1%
1<
b1 Q
#5000
0%
0<
b1010111 '
b10 7
1E
1D
1C
1A
0@
1?
#5500
1%
1<
b10 Q
#6000
0%
0<
b110000 '
b11 7
0E
0D
0C
1@
0?
#6500
1%
1<
b11 Q
#7000
0%
0<
b11101011 '
b100 7
1E
1D
1B
0A
1?
1>
#7500
1%
1<
b100 Q
#8000
0%
0<
b10101111 '
b101 7
1C
0?
#8500
1%
1<
b101 Q
#9000
0%
0<
b11101100 '
b110 7
0E
0D
1?
#9500
1%
1<
b110 Q
#10000
0%
0<
b1001001 '
b111 7
1E
0C
0@
0>
#10500
1%
1<
b111 Q
#11000
0%
0<
b10010011 '
b1000 7
1D
0B
1A
0?
1>
#11500
1%
1<
b1000 Q
#12000
0%
0<
b100010 '
b1001 7
0E
0A
1@
0>
#12500
1%
1<
b1001 Q
#13000
0%
0<
b1100111 '
b1010 7
1E
1C
1?
#13500
1%
1<
b1010 Q
#14000
0%
0<
b10100000 '
b1011 7
0E
0D
0C
0?
1>
#14500
1%
1<
b1011 Q
#15000
0%
0<
b101 '
b1100 7
1E
1C
0@
0>
#15500
1%
1<
b1100 Q
#16000
0%
0<
b1000100 '
b1101 7
0E
1?
#16500
1%
1<
b1101 Q
#17000
0%
0<
b1100010 '
b1110 7
1D
0C
1@
#17500
1%
1<
b1110 Q
#18000
0%
0<
b1100110 '
b1111 7
1C
#18500
1%
1<
b1111 Q
#19000
0%
0<
b11001100 '
b10000 7
0D
1B
0@
1>
#19500
1%
1<
b10000 Q
#20000
0%
0<
b1110110 '
b10001 7
1D
0B
1A
1@
0>
#20500
1%
1<
b10001 Q
#21000
0%
0<
b10010111 '
b10010 7
1E
0@
0?
1>
#21500
1%
1<
b10010 Q
#22000
0%
0<
b101000 '
b10011 7
0E
0D
0C
1B
0A
1@
0>
#22500
1%
1<
b10011 Q
#23000
0%
0<
b1001 '
b10100 7
1E
0@
#23500
1%
1<
b10100 Q
#24000
0%
0<
b11111111 '
b10101 7
1D
1C
1A
1@
1?
1>
#24500
1%
1<
b10101 Q
#25000
0%
0<
b1000000 '
b10110 7
0E
0D
0C
0B
0A
0@
0>
#25500
1%
1<
b10110 Q
#26000
0%
0<
b11000 '
b10111 7
1B
1A
0?
#26500
1%
1<
b10111 Q
#27000
0%
0<
b10000000 '
b11000 7
0B
0A
1>
#27500
1%
1<
b11000 Q
#28000
0%
0<
b11110000 '
b11001 7
1A
1@
1?
#28500
1%
1<
b11001 Q
#29000
0%
0<
b11101001 '
b11010 7
1E
1B
0A
#29500
1%
1<
b11010 Q
#30000
0%
0<
b11101010 '
b11011 7
0E
1D
#30500
1%
1<
b11011 Q
#31000
0%
0<
b10000111 '
b11100 7
1E
1C
0B
0@
0?
#31500
1%
1<
b11100 Q
#32000
0%
0<
b11011101 '
b11101 7
0D
1B
1A
1?
#32500
1%
1<
b11101 Q
#33000
0%
0<
b11101101 '
b11110 7
0A
1@
#33500
1%
1<
b11110 Q
#34000
0%
0<
b11010100 '
b11111 7
0E
0B
1A
0@
#34500
1%
1<
b11111 Q
#35000
0%
0<
b11010011 '
b100000 7
1E
1D
0C
#35500
1%
1<
b100000 Q
#36000
0%
0<
b10111011 '
b100001 7
1B
1@
0?
#36500
1%
1<
b100001 Q
#37000
0%
0<
b11110100 '
b100010 7
0E
0D
1C
0B
1?
#37500
1%
1<
b100010 Q
#38000
0%
0<
b1110111 '
b100011 7
1E
1D
0>
#38500
1%
1<
b100011 Q
#39000
0%
0<
b1010010 '
b100100 7
0E
0C
0@
#39500
1%
1<
b100100 Q
#40000
0%
0<
bx '
b100101 7
b1 6
bz '
zE
zD
zC
zB
zA
z@
z?
z>
#40500
1%
1<
1K
b1100110 J
b11 O
12
01
10
1/
0.
0-
1,
1+
0*
#41000
0%
0<
#41500
1%
1<
b1 :
b11001100 J
b100 O
00
1.
0,
1*
#42000
0%
0<
#42500
1%
1<
b11001100 4
b10 :
b1110110 J
b10 O
b11 P
10
0.
1-
1,
0*
#43000
0%
0<
#43500
1%
1<
b1110110 4
b11 :
b11111111 J
b11 O
11
1.
1*
#44000
0%
0<
#44500
1%
1<
b11111111 4
b100 :
b1000000 J
b100 O
01
00
0/
0.
0-
0,
0*
#45000
0%
0<
#45500
1%
1<
b1000000 4
b101 :
b11000 J
b10 O
b100 P
1.
1-
0+
#46000
0%
0<
#46500
1%
1<
b11000 4
b110 :
b11101010 J
b11 O
10
0-
1,
1+
1*
#47000
0%
0<
#47500
1%
1<
b11101010 4
b111 :
b10000111 J
b100 O
11
1/
0.
0,
0+
#48000
0%
0<
#48500
1%
1<
b10000111 4
b1000 :
b11011101 J
0L
0K
b0 Q
00
1.
1-
1+
03
02
#49000
0%
0<
b1 (
1)
b0 7
1H
0G
0F
1I
#49500
1%
1<
b11011101 4
#50000
0%
0<
b100000 '
bz (
0)
b1 7
zH
zG
zF
0E
0D
0C
0B
0A
1@
0?
0>
0I
1L
13
#50500
1%
1<
b1 Q
#51000
0%
0<
b1010111 '
b10 7
1E
1D
1C
1A
0@
1?
#51500
1%
1<
b10 Q
#52000
0%
0<
b110000 '
b11 7
0E
0D
0C
1@
0?
#52500
1%
1<
b11 Q
#53000
0%
0<
b11101011 '
b100 7
1E
1D
1B
0A
1?
1>
#53500
1%
1<
b100 Q
#54000
0%
0<
b10101111 '
b101 7
1C
0?
#54500
1%
1<
b101 Q
#55000
0%
0<
b11101100 '
b110 7
0E
0D
1?
#55500
1%
1<
b110 Q
#56000
0%
0<
b1001001 '
b111 7
1E
0C
0@
0>
#56500
1%
1<
b111 Q
#57000
0%
0<
b10010011 '
b1000 7
1D
0B
1A
0?
1>
#57500
1%
1<
b1000 Q
#58000
0%
0<
b100010 '
b1001 7
0E
0A
1@
0>
#58500
1%
1<
b1001 Q
#59000
0%
0<
b1100111 '
b1010 7
1E
1C
1?
#59500
1%
1<
b1010 Q
#60000
0%
0<
b10100000 '
b1011 7
0E
0D
0C
0?
1>
#60500
1%
1<
b1011 Q
#61000
0%
0<
b101 '
b1100 7
1E
1C
0@
0>
#61500
1%
1<
b1100 Q
#62000
0%
0<
b1000100 '
b1101 7
0E
1?
#62500
1%
1<
b1101 Q
#63000
0%
0<
b1100010 '
b1110 7
1D
0C
1@
#63500
1%
1<
b1110 Q
#64000
0%
0<
b1100110 '
b1111 7
1C
#64500
1%
1<
b1111 Q
#65000
0%
0<
b11001100 '
b10000 7
0D
1B
0@
1>
#65500
1%
1<
b10000 Q
#66000
0%
0<
b1110110 '
b10001 7
1D
0B
1A
1@
0>
#66500
1%
1<
b10001 Q
#67000
0%
0<
b10010111 '
b10010 7
1E
0@
0?
1>
#67500
1%
1<
b10010 Q
#68000
0%
0<
b101000 '
b10011 7
0E
0D
0C
1B
0A
1@
0>
#68500
1%
1<
b10011 Q
#69000
0%
0<
b1001 '
b10100 7
1E
0@
#69500
1%
1<
b10100 Q
#70000
0%
0<
b11111111 '
b10101 7
1D
1C
1A
1@
1?
1>
#70500
1%
1<
b10101 Q
#71000
0%
0<
b1000000 '
b10110 7
0E
0D
0C
0B
0A
0@
0>
#71500
1%
1<
b10110 Q
#72000
0%
0<
b11000 '
b10111 7
1B
1A
0?
#72500
1%
1<
b10111 Q
#73000
0%
0<
b10000000 '
b11000 7
0B
0A
1>
#73500
1%
1<
b11000 Q
#74000
0%
0<
b11110000 '
b11001 7
1A
1@
1?
#74500
1%
1<
b11001 Q
#75000
0%
0<
b11101001 '
b11010 7
1E
1B
0A
#75500
1%
1<
b11010 Q
#76000
0%
0<
b11101010 '
b11011 7
0E
1D
#76500
1%
1<
b11011 Q
#77000
0%
0<
b10000111 '
b11100 7
1E
1C
0B
0@
0?
#77500
1%
1<
b11100 Q
#78000
0%
0<
b11011101 '
b11101 7
0D
1B
1A
1?
#78500
1%
1<
b11101 Q
#79000
0%
0<
b11101101 '
b11110 7
0A
1@
#79500
1%
1<
b11110 Q
#80000
0%
0<
b11010100 '
b11111 7
0E
0B
1A
0@
#80500
1%
1<
b11111 Q
#81000
0%
0<
b11010011 '
b100000 7
1E
1D
0C
#81500
1%
1<
b100000 Q
#82000
0%
0<
b10111011 '
b100001 7
1B
1@
0?
#82500
1%
1<
b100001 Q
#83000
0%
0<
b11110100 '
b100010 7
0E
0D
1C
0B
1?
#83500
1%
1<
b100010 Q
#84000
0%
0<
b1110111 '
b100011 7
1E
1D
0>
#84500
1%
1<
b100011 Q
#85000
0%
0<
b1010010 '
b100100 7
0E
0C
0@
#85500
1%
1<
b100100 Q
#86000
0%
0<
bx '
b100101 7
b10 6
bz '
zE
zD
zC
zB
zA
z@
z?
z>
#86500
1%
1<
0L
b0 Q
03
#87000
0%
0<
b10 (
1)
0H
1G
0F
1I
#87500
1%
1<
#88000
0%
0<
0)
b11 6
1)
1L
b10 R
13
#88500
1%
1<
#89000
0%
0<
0)
b100 6
bz (
0I
zH
zG
zF
#89500
1%
1<
0L
03
#90000
0%
0<
b101 (
1)
1H
0G
1F
1I
#90500
1%
1<
#91000
0%
0<
0)
b101 6
1)
1L
b101 R
13
#91500
1%
1<
#92000
0%
0<
0)
b110 6
bz (
0I
zH
zG
zF
#92500
1%
1<
0L
03
#93000
0%
0<
b11 (
1)
1H
1G
0F
1I
#93500
1%
1<
#94000
0%
0<
0)
b111 6
b101 (
1)
0G
1F
1L
b11 R
13
#94500
1%
1<
#95000
0%
0<
0)
b1000 6
bz (
0I
zH
zG
zF
b101 R
#95500
1%
1<
0L
03
#96000
0%
0<
b11 (
1)
1H
1G
0F
1I
#96500
1%
1<
#97000
0%
0<
0)
b1001 6
1)
1L
b11 R
13
#97500
1%
1<
#98000
0%
0<
0)
b1010 6
bz (
0I
zH
zG
zF
#98500
1%
1<
0L
03
#99000
0%
0<
b100 (
1)
0H
0G
1F
1I
#99500
1%
1<
#100000
0%
0<
0)
b1011 6
1)
1L
b100 R
13
#100500
1%
1<
#101000
0%
0<
0)
b1100 6
bz (
0I
zH
zG
zF
#101500
1%
1<
0L
03
#102000
0%
0<
b11 (
1)
1H
1G
0F
1I
#102500
1%
1<
#103000
0%
0<
0)
b1101 6
b100 (
1)
0H
0G
1F
1L
b11 R
13
#103500
1%
1<
#104000
0%
0<
0)
b1110 6
bz (
0I
zH
zG
zF
b100 R
#104500
1%
1<
0L
03
#105000
0%
0<
b1 (
1)
b0 7
1H
0G
0F
1I
#105500
1%
1<
#106000
0%
0<
b100000 '
bz (
0)
b1 7
zH
zG
zF
0E
0D
0C
0B
0A
1@
0?
0>
0I
1L
b1 R
13
#106500
1%
1<
b1 Q
#107000
0%
0<
b1010111 '
b10 7
1E
1D
1C
1A
0@
1?
#107500
1%
1<
b10 Q
#108000
0%
0<
b110000 '
b11 7
0E
0D
0C
1@
0?
#108500
1%
1<
b11 Q
#109000
0%
0<
b11101011 '
b100 7
1E
1D
1B
0A
1?
1>
#109500
1%
1<
b100 Q
#110000
0%
0<
b10101111 '
b101 7
1C
0?
#110500
1%
1<
b101 Q
#111000
0%
0<
b11101100 '
b110 7
0E
0D
1?
#111500
1%
1<
b110 Q
#112000
0%
0<
b1001001 '
b111 7
1E
0C
0@
0>
#112500
1%
1<
b111 Q
#113000
0%
0<
b10010011 '
b1000 7
1D
0B
1A
0?
1>
#113500
1%
1<
b1000 Q
#114000
0%
0<
b100010 '
b1001 7
0E
0A
1@
0>
#114500
1%
1<
b1001 Q
#115000
0%
0<
b1100111 '
b1010 7
1E
1C
1?
#115500
1%
1<
b1010 Q
#116000
0%
0<
b10100000 '
b1011 7
0E
0D
0C
0?
1>
#116500
1%
1<
b1011 Q
#117000
0%
0<
b101 '
b1100 7
1E
1C
0@
0>
#117500
1%
1<
b1100 Q
#118000
0%
0<
b1000100 '
b1101 7
0E
1?
#118500
1%
1<
b1101 Q
#119000
0%
0<
b1100010 '
b1110 7
1D
0C
1@
#119500
1%
1<
b1110 Q
#120000
0%
0<
b1100110 '
b1111 7
1C
#120500
1%
1<
b1111 Q
#121000
0%
0<
b11001100 '
b10000 7
0D
1B
0@
1>
#121500
1%
1<
b10000 Q
#122000
0%
0<
b1110110 '
b10001 7
1D
0B
1A
1@
0>
#122500
1%
1<
b10001 Q
#123000
0%
0<
b10010111 '
b10010 7
1E
0@
0?
1>
#123500
1%
1<
b10010 Q
#124000
0%
0<
b101000 '
b10011 7
0E
0D
0C
1B
0A
1@
0>
#124500
1%
1<
b10011 Q
#125000
0%
0<
b1001 '
b10100 7
1E
0@
#125500
1%
1<
b10100 Q
#126000
0%
0<
b11111111 '
b10101 7
1D
1C
1A
1@
1?
1>
#126500
1%
1<
b10101 Q
#127000
0%
0<
b1000000 '
b10110 7
0E
0D
0C
0B
0A
0@
0>
#127500
1%
1<
b10110 Q
#128000
0%
0<
b11000 '
b10111 7
1B
1A
0?
#128500
1%
1<
b10111 Q
#129000
0%
0<
b10000000 '
b11000 7
0B
0A
1>
#129500
1%
1<
b11000 Q
#130000
0%
0<
b11110000 '
b11001 7
1A
1@
1?
#130500
1%
1<
b11001 Q
#131000
0%
0<
b11101001 '
b11010 7
1E
1B
0A
#131500
1%
1<
b11010 Q
#132000
0%
0<
b11101010 '
b11011 7
0E
1D
#132500
1%
1<
b11011 Q
#133000
0%
0<
b10000111 '
b11100 7
1E
1C
0B
0@
0?
#133500
1%
1<
b11100 Q
#134000
0%
0<
b11011101 '
b11101 7
0D
1B
1A
1?
#134500
1%
1<
b11101 Q
#135000
0%
0<
b11101101 '
b11110 7
0A
1@
#135500
1%
1<
b11110 Q
#136000
0%
0<
b11010100 '
b11111 7
0E
0B
1A
0@
#136500
1%
1<
b11111 Q
#137000
0%
0<
b11010011 '
b100000 7
1E
1D
0C
#137500
1%
1<
b100000 Q
#138000
0%
0<
b10111011 '
b100001 7
1B
1@
0?
#138500
1%
1<
b100001 Q
#139000
0%
0<
b11110100 '
b100010 7
0E
0D
1C
0B
1?
#139500
1%
1<
b100010 Q
#140000
0%
0<
b1110111 '
b100011 7
1E
1D
0>
#140500
1%
1<
b100011 Q
#141000
0%
0<
b1010010 '
b100100 7
0E
0C
0@
#141500
1%
1<
b100100 Q
#142000
0%
0<
bx '
b100101 7
b1111 6
bz '
zE
zD
zC
zB
zA
z@
z?
z>
#142500
1%
1<
0L
b0 Q
03
#143000
0%
0<
b11 (
1)
1H
1G
0F
1I
#143500
1%
1<
#144000
0%
0<
0)
b10000 6
b100 (
1)
0H
0G
1F
1L
b11 R
13
#144500
1%
1<
#145000
0%
0<
0)
b10001 6
bz (
0I
zH
zG
zF
b100 R
#145500
1%
1<
0L
03
#146000
0%
0<
b100 (
1)
0H
0G
1F
1I
#146500
1%
1<
#147000
0%
0<
0)
b10010 6
b10 (
1)
1G
0F
1L
13
#147500
1%
1<
#148000
0%
0<
0)
b10011 6
bz (
0I
zH
zG
zF
b10 R
#148500
1%
1<
0L
03
#149000
0%
0<
b100 (
1)
0H
0G
1F
1I
#149500
1%
1<
#150000
0%
0<
0)
b10100 6
b10 (
1)
1G
0F
1L
b100 R
13
#150500
1%
1<
#151000
0%
0<
0)
b10101 6
bz (
0I
zH
zG
zF
b10 R
#151500
1%
1<
0L
03
#152000
0%
0<
b100 (
1)
0H
0G
1F
1I
#152500
1%
1<
#153000
0%
0<
0)
b10110 6
b10 (
1)
1G
0F
1L
b100 R
13
#153500
1%
1<
#154000
0%
0<
0)
b10111 6
bz (
0I
zH
zG
zF
b10 R
#154500
1%
1<
0L
03
#155000
0%
0<
b101 (
1)
1H
0G
1F
1I
#155500
1%
1<
#156000
0%
0<
0)
b11000 6
b10 (
1)
0H
1G
0F
1L
b101 R
13
#156500
1%
1<
#157000
0%
0<
0)
b11001 6
bz (
0I
zH
zG
zF
b10 R
#157500
1%
1<
0L
03
#158000
0%
0<
b10 (
1)
0H
1G
0F
1I
#158500
1%
1<
#159000
0%
0<
0)
b11010 6
b101 (
1)
1H
0G
1F
1L
13
#159500
1%
1<
#160000
0%
0<
0)
b11011 6
bz (
0I
zH
zG
zF
b101 R
#160500
1%
1<
0L
03
#161000
0%
0<
b101 (
1)
1H
0G
1F
1I
#161500
1%
1<
#162000
0%
0<
0)
b11100 6
1)
1L
13
#162500
1%
1<
#163000
0%
0<
0)
b11101 6
bz (
0I
zH
zG
zF
#163500
1%
1<
0L
03
#164000
0%
0<
b1 (
1)
b0 7
1H
0G
0F
1I
#164500
1%
1<
#165000
0%
0<
b100000 '
bz (
0)
b1 7
zH
zG
zF
0E
0D
0C
0B
0A
1@
0?
0>
0I
1L
b1 R
13
#165500
1%
1<
b1 Q
#166000
0%
0<
b1010111 '
b10 7
1E
1D
1C
1A
0@
1?
#166500
1%
1<
b10 Q
#167000
0%
0<
b110000 '
b11 7
0E
0D
0C
1@
0?
#167500
1%
1<
b11 Q
#168000
0%
0<
b11101011 '
b100 7
1E
1D
1B
0A
1?
1>
#168500
1%
1<
b100 Q
#169000
0%
0<
b10101111 '
b101 7
1C
0?
#169500
1%
1<
b101 Q
#170000
0%
0<
b11101100 '
b110 7
0E
0D
1?
#170500
1%
1<
b110 Q
#171000
0%
0<
b1001001 '
b111 7
1E
0C
0@
0>
#171500
1%
1<
b111 Q
#172000
0%
0<
b10010011 '
b1000 7
1D
0B
1A
0?
1>
#172500
1%
1<
b1000 Q
#173000
0%
0<
b100010 '
b1001 7
0E
0A
1@
0>
#173500
1%
1<
b1001 Q
#174000
0%
0<
b1100111 '
b1010 7
1E
1C
1?
#174500
1%
1<
b1010 Q
#175000
0%
0<
b10100000 '
b1011 7
0E
0D
0C
0?
1>
#175500
1%
1<
b1011 Q
#176000
0%
0<
b101 '
b1100 7
1E
1C
0@
0>
#176500
1%
1<
b1100 Q
#177000
0%
0<
b1000100 '
b1101 7
0E
1?
#177500
1%
1<
b1101 Q
#178000
0%
0<
b1100010 '
b1110 7
1D
0C
1@
#178500
1%
1<
b1110 Q
#179000
0%
0<
b1100110 '
b1111 7
1C
#179500
1%
1<
b1111 Q
#180000
0%
0<
b11001100 '
b10000 7
0D
1B
0@
1>
#180500
1%
1<
b10000 Q
#181000
0%
0<
b1110110 '
b10001 7
1D
0B
1A
1@
0>
#181500
1%
1<
b10001 Q
#182000
0%
0<
b10010111 '
b10010 7
1E
0@
0?
1>
#182500
1%
1<
b10010 Q
#183000
0%
0<
b101000 '
b10011 7
0E
0D
0C
1B
0A
1@
0>
#183500
1%
1<
b10011 Q
#184000
0%
0<
b1001 '
b10100 7
1E
0@
#184500
1%
1<
b10100 Q
#185000
0%
0<
b11111111 '
b10101 7
1D
1C
1A
1@
1?
1>
#185500
1%
1<
b10101 Q
#186000
0%
0<
b1000000 '
b10110 7
0E
0D
0C
0B
0A
0@
0>
#186500
1%
1<
b10110 Q
#187000
0%
0<
b11000 '
b10111 7
1B
1A
0?
#187500
1%
1<
b10111 Q
#188000
0%
0<
b10000000 '
b11000 7
0B
0A
1>
#188500
1%
1<
b11000 Q
#189000
0%
0<
b11110000 '
b11001 7
1A
1@
1?
#189500
1%
1<
b11001 Q
#190000
0%
0<
b11101001 '
b11010 7
1E
1B
0A
#190500
1%
1<
b11010 Q
#191000
0%
0<
b11101010 '
b11011 7
0E
1D
#191500
1%
1<
b11011 Q
#192000
0%
0<
b10000111 '
b11100 7
1E
1C
0B
0@
0?
#192500
1%
1<
b11100 Q
#193000
0%
0<
b11011101 '
b11101 7
0D
1B
1A
1?
#193500
1%
1<
b11101 Q
#194000
0%
0<
b11101101 '
b11110 7
0A
1@
#194500
1%
1<
b11110 Q
